fa_tui/__init__.py
fa_tui/app.py
fa_tui-0.1.0.dist-info/METADATA
fa_tui-0.1.0.dist-info/WHEEL
fa_tui-0.1.0.dist-info/entry_points.txt
fa_tui-0.1.0.dist-info/top_level.txt
fa_tui-0.1.0.dist-info/RECORD
