Metadata-Version: 2.1
Name: fa-tui
Version: 0.1.0
Summary: 一个文本TUI工具，用于选择frida进程和JS脚本。适用于Android系统
Author-email: hongenge <hongen.me@gmail.com>
Project-URL: Homepage, https://github.com/hongenge/fa-tui
Requires-Python: >=3.8
Requires-Dist: textual>=3.5.0
